pecok/__init__.py
pecok/admm.py
pecok/clustering.py
pecok/gamma.py
pecok-1.0.3.dist-info/LICENSE.txt
pecok-1.0.3.dist-info/METADATA
pecok-1.0.3.dist-info/WHEEL
pecok-1.0.3.dist-info/top_level.txt
pecok-1.0.3.dist-info/RECORD
