Metadata-Version: 2.1
Name: pecok
Version: 1.0.3
Summary: Implementation of Pecok
Home-page: https://github.com/martinroyer/pecok
Author: Martin Royer
Author-email: martinpierreroyer@gmail.com
License: MIT/X
Platform: UNKNOWN
Classifier: Development Status :: 4 - Beta
Classifier: Intended Audience :: Science/Research
Classifier: License :: OSI Approved :: MIT License
Classifier: Operating System :: OS Independent
Classifier: Programming Language :: Python
Classifier: Programming Language :: Python :: 3
Classifier: Topic :: Scientific/Engineering
Requires-Dist: numpy
Requires-Dist: scipy
Requires-Dist: scikit-learn
